pyrly/__init__.py
pyrly/stopwatch/__init__.py
pyrly/work_history/__init__.py
pyrly-0.0.3.dist-info/LICENSE
pyrly-0.0.3.dist-info/METADATA
pyrly-0.0.3.dist-info/WHEEL
pyrly-0.0.3.dist-info/entry_points.txt
pyrly-0.0.3.dist-info/top_level.txt
pyrly-0.0.3.dist-info/RECORD
