Metadata-Version: 2.1
Name: pyrly
Version: 0.0.3
Summary: Package for administrate hourly work.
Home-page: https://github.com/ccmorenosa/Pyrly.git
Author: Catalina Moreno
Author-email: ccatamorenos@gmail.com
Maintainer: Catalina Moreno
Maintainer-email: ccatamorenos@gmail.com
License: MIT license
License-File: LICENSE
